{"dAuN": "Nina Keary", "lastKnownAffiliation": {"lt": "Bielefeld University", "id": 20121455}, "publicationCount": {"lt": "5", "q": "papers by nina keary", "iq": "And(Ty='0',Composite(AA.AuId=100712948))", "sm": 0}, "citationCount": {"lt": "152", "q": "papers citing papers by nina keary", "iq": "And(Ty='0',Join(RId,Composite(AA.AuId=100712948)))", "sm": 0}, "coAuthors": [{"lt": "Hans-Joachim Bischof", "id": 1978879868}, {"lt": "Joe Voss", "id": 2272978440}, {"lt": "Siegrid L\u00f6wel", "id": 1121876812}, {"lt": "Tim Ruploh", "id": 55142760}, {"lt": "Wolfgang Wiltschko", "id": 154487814}, {"lt": "Roswitha Wiltschko", "id": 156469931}, {"lt": "Peter Thalau", "id": 2305642842}, {"lt": "Konrad Lehmann", "id": 2085570570}, {"lt": "Neethu Michael", "id": 2150063069}, {"lt": "Uwe Mayer", "id": 2675291000}, {"lt": "Dennis Eckmeier", "id": 2741498552}], "affiliations": [{"lt": "Bielefeld University", "id": 20121455}, {"lt": "Goethe University Frankfurt", "id": 114090438}, {"lt": "University of Jena", "id": 76198965}, {"lt": "University of G\u00f6ttingen", "id": 74656192}, {"lt": "University of Trento", "id": 193223587}], "fieldsOfStudy": [{"lt": "Biology", "id": 86803240}, {"lt": "Anatomy", "id": 105702510}, {"lt": "Taeniopygia", "id": 2778917935}, {"lt": "Magnetic field", "id": 115260700}, {"lt": "Earth's magnetic field", "id": 199635899}, {"lt": "Perception", "id": 26760741}, {"lt": "Visual field", "id": 2776058522}, {"lt": "Visual cortex", "id": 2779345533}, {"lt": "Oscillation", "id": 26733877}, {"lt": "Nuclear magnetic resonance", "id": 46141821}, {"lt": "Magnetic nanoparticles", "id": 87023908}, {"lt": "Magnetic particle inspection", "id": 109647046}, {"lt": "Communication", "id": 46312422}, {"lt": "Compass", "id": 2778361833}, {"lt": "Premovement neuronal activity", "id": 74254510}, {"lt": "Tectum", "id": 2779480072}, {"lt": "Songbird", "id": 2779600091}, {"lt": "Fovea centralis", "id": 2779736970}, {"lt": "Finch", "id": 2781352930}, {"lt": "Superior colliculus", "id": 2781416072}]}