{"dAuN": "Ignacio Sandia", "lastKnownAffiliation": null, "publicationCount": {"lt": "9", "q": "papers by ignacio sandia", "iq": "And(Ty='0',Composite(AA.AuId=100742358))", "sm": 0}, "citationCount": {"lt": "305", "q": "papers citing papers by ignacio sandia", "iq": "And(Ty='0',Join(RId,Composite(AA.AuId=100742358)))", "sm": 0}, "coAuthors": [{"lt": "Trino Baptista", "id": 2013467370}, {"lt": "Enma Araujo de Baptista", "id": 2145082884}, {"lt": "Edgardo Carrizo", "id": 2697807327}, {"lt": "Lisette Connell", "id": 2126340776}, {"lt": "Johana Mogoll\u00f3n", "id": 2112237016}, {"lt": "Dennys Valbuena", "id": 2130189389}, {"lt": "Dexy Prieto", "id": 2145766377}, {"lt": "Iliana Fern\u00e1ndez", "id": 2249114534}, {"lt": "Virginia Fern\u00e1ndez", "id": 2272813081}, {"lt": "Euderruh Uzc\u00e1tegui", "id": 2042516461}, {"lt": "Eduardo T\u00e1lamo", "id": 2046670963}, {"lt": "Erika Fern\u00e1ndez", "id": 2145740645}, {"lt": "Serge Beaulieu", "id": 2101885843}, {"lt": "Yamily ElFakih", "id": 2476267047}, {"lt": "Nairy Rangel", "id": 2149883094}, {"lt": "Ana Serrano", "id": 2576096208}, {"lt": "Mercedes Servigna", "id": 1959209439}, {"lt": "Quilianio Contreras", "id": 2028175233}, {"lt": "Tatiana Galeazzi", "id": 2105004020}, {"lt": "Soaira De Mendoza", "id": 2106101725}], "affiliations": [{"lt": "Venezuelan Institute for Scientific Research", "id": 191242182}, {"lt": "McGill University", "id": 5023651}], "fieldsOfStudy": [{"lt": "Clozapine", "id": 2780864610}, {"lt": "Psychiatry", "id": 118552586}, {"lt": "Medicine", "id": 71924100}, {"lt": "Olanzapine", "id": 2776619155}, {"lt": "Internal medicine", "id": 126322002}, {"lt": "Endocrinology", "id": 134018914}, {"lt": "Insulin resistance", "id": 2777391703}, {"lt": "Metformin", "id": 2780323712}, {"lt": "Insulin", "id": 2779306644}, {"lt": "Atypical antipsychotic", "id": 2776921671}, {"lt": "Placebo-controlled study", "id": 202061045}, {"lt": "Type 2 diabetes", "id": 2777180221}, {"lt": "Glycated hemoglobin", "id": 2777538456}, {"lt": "Psychology", "id": 15744967}, {"lt": "Anesthesia", "id": 42219234}, {"lt": "Leptin", "id": 2780613262}, {"lt": "Typical antipsychotic", "id": 2775870346}, {"lt": "Perphenazine", "id": 2776743534}, {"lt": "Ziprasidone", "id": 2777270317}, {"lt": "Risperidone", "id": 2780057945}]}