{"dAuN": "Victor Girondin", "lastKnownAffiliation": {"lt": "university of lille", "id": 2279609970}, "publicationCount": {"lt": "9", "q": "papers by victor girondin", "iq": "And(Ty='0',Composite(AA.AuId=109065868))", "sm": 0}, "citationCount": {"lt": "25", "q": "papers citing papers by victor girondin", "iq": "And(Ty='0',Join(RId,Composite(AA.AuId=109065868)))", "sm": 0}, "coAuthors": [{"lt": "Jean-Philippe Cassar", "id": 2287166825}, {"lt": "Komi Midzodzi Pekpe", "id": 1149766127}, {"lt": "Herv\u00e9 Morel", "id": 2667972398}, {"lt": "Mehena Loudahi", "id": 2888411436}, {"lt": "Jean-Philippe Cassar", "id": 2773764704}, {"lt": "Morel Herv\u00e9", "id": 2621092636}, {"lt": "Komi Midzodzi Pekpe", "id": 2788755315}], "affiliations": [{"lt": "university of lille", "id": 2279609970}, {"lt": "Airbus Helicopters", "id": 1340412301}, {"lt": "Airbus", "id": 33375025}], "fieldsOfStudy": [{"lt": "Vibration", "id": 198394728}, {"lt": "Fault detection and isolation", "id": 152745839}, {"lt": "Control engineering", "id": 133731056}, {"lt": "Engineering", "id": 127413603}, {"lt": "Bearing", "id": 127298686}, {"lt": "Cyclostationary process", "id": 178351263}, {"lt": "Accelerometer", "id": 89805583}, {"lt": "Structural engineering", "id": 66938386}, {"lt": "Harmonics", "id": 188414643}, {"lt": "Mathematics", "id": 33923547}, {"lt": "Control theory", "id": 65244806}, {"lt": "Kinematics", "id": 39920418}, {"lt": "Amplitude", "id": 180205008}, {"lt": "Rolling-element bearing", "id": 2780155820}, {"lt": "Signal processing", "id": 104267543}, {"lt": "Electronic engineering", "id": 24326235}, {"lt": "Transmission", "id": 40827391}, {"lt": "Coherence", "id": 91524940}, {"lt": "Sampling", "id": 140779682}, {"lt": "Redundancy", "id": 152124472}]}