{"dAuN": "Harald Stummer", "lastKnownAffiliation": {"lt": "University of Health Sciences Antigua", "id": 872922937}, "publicationCount": {"lt": "55", "q": "papers by harald stummer", "iq": "And(Ty='0',Composite(AA.AuId=1207974270))", "sm": 0}, "citationCount": {"lt": "152", "q": "papers citing papers by harald stummer", "iq": "And(Ty='0',Join(RId,Composite(AA.AuId=1207974270)))", "sm": 0}, "coAuthors": [{"lt": "Tobias Romeyke", "id": 2364889896}, {"lt": "Elisabeth N\u00f6hammer", "id": 1840074463}, {"lt": "Claudia Schusterschitz", "id": 267663915}, {"lt": "Hans Christoph Scheuer", "id": 2274242433}, {"lt": "Elisabeth Noehammer", "id": 2742404952}, {"lt": "Josef Farnschl\u00e4der", "id": 222735618}, {"lt": "Birgit R\u00f6sler-Schidlack", "id": 2177887685}, {"lt": "Herwig Ostermann", "id": 2503946517}, {"lt": "Hans Ch.Scheuer", "id": 2785634075}, {"lt": "Thilo K. Eith", "id": 2707036607}, {"lt": "Willi Geser", "id": 96161986}, {"lt": "Petra Schadenhofer", "id": 100347946}, {"lt": "Harald Meyer", "id": 2618810032}, {"lt": "Manfred Hofst\u00e4tter", "id": 2794394862}, {"lt": "Michael M\u00fcller", "id": 2621519619}, {"lt": "Gerhard Huber", "id": 2147319967}, {"lt": "Sabine Katzdobler", "id": 2526069811}, {"lt": "Rainer Thomann", "id": 2026534740}, {"lt": "Matthias Murugiah", "id": 2674163909}, {"lt": "Arno Elmer", "id": 2692424704}], "affiliations": [{"lt": "University of Health Sciences Antigua", "id": 872922937}], "fieldsOfStudy": [{"lt": "Medicine", "id": 71924100}, {"lt": "Nursing", "id": 159110408}, {"lt": "Inpatient care", "id": 2775909303}, {"lt": "Family medicine", "id": 512399662}, {"lt": "Clinical pathway", "id": 2778373050}, {"lt": "Qualitative research", "id": 190248442}, {"lt": "Workplace health promotion", "id": 2780631933}, {"lt": "Physical therapy", "id": 1862650}, {"lt": "Quality assurance", "id": 106436119}, {"lt": "Psychology", "id": 15744967}, {"lt": "Risk analysis", "id": 112930515}, {"lt": "Public Relations", "id": 39549134}, {"lt": "Health promotion", "id": 185618831}, {"lt": "Risk management", "id": 32896092}, {"lt": "Cost accounting", "id": 94107157}, {"lt": "Total cost", "id": 182299520}, {"lt": "Legal liability", "id": 199286143}, {"lt": "Cost reduction", "id": 2778820799}, {"lt": "Occupational safety and health", "id": 187155963}, {"lt": "German", "id": 154775046}]}